{"mid.$cAAAB9Q9aNWWKtYZ_QmEhEE3E6DCy":"who is pat","mid.$gABm9E9p_pl6KtYaf02EhEFXSDJZP":"Yung tipong mag papa check up Sana ako SA manicurista ako pumunta 🤣","mid.$gAByS_F7gfFaKtYa_YWEhEF3LiKe9":"Yeah, thank bro!","mid.$gABm9E9p_pl6KtYbT_GEhEGLmRjmK":"who is pat","mid.$gABm9E9p_pl6KtYbpEWEhEGgrOVDd":"sabog","mid.$gABm9E9p_pl6KtYeIgmEhEJAITJy9":"who is Bharat Singh","mid.$gABQVzSDc9xeKtYpFpGEhET88dwBF":"This one don come online this early morning","mid.$gABQVzSDc9xeKtYqDtGEhEU6_dlUB":"🙄","mid.$gABm9E9p_pl6KtYqnRGEhEVcj58pN":["img","https://scontent.xx.fbcdn.net/v/t1.15752-9/315517570_706087774089526_3807915442414391820_n.jpg?stp=dst-jpg_p480x480&_nc_cat=109&ccb=1-7&_nc_sid=ae9488&_nc_eui2=AeHnQmnCUvGfzXeybZh-atwqItV4ut4N0RIi1Xi63g3REkh-qZNT0f6b6_crnNXHCtXmkIC6Q4UoNwgK3PlhWTRs&_nc_ohc=d_g_4xP2aiAAX_vMk5m&_nc_ad=z-m&_nc_cid=0&_nc_ht=scontent.xx&oh=03_AdQ7HHi_qR8JA2wCYNd3GoT-bUI4zNfZGxbKm70SP-56Dw&oe=639D5915"],"mid.$gABQVzSDc9xeKtYr87GEhEW0L7t9F":"This bot 😅","mid.$gABQVzSDc9xeKtYt_4mEhEY3MUfhl":"You dey sleep at all?\nCuz.... 😆","mid.$gABm9E9p_pl6KtY15zWEhEgw1XuwK":"pwede ba php sa","mid.$gABm9E9p_pl6KtY2hSGEhEhShT18S":"Puwede","mid.$gABm9E9p_pl6KtY4hhmEhEjZIdhZ0":"sublime?"}