[{"key":"sb","value":"ivgEYzHzzCO2rmNYNF2gtHb0","domain":"facebook.com","path":"/","hostOnly":false,"creation":"2022-11-30T22:56:48.634Z","lastAccessed":"2022-11-30T23:00:00.830Z"},{"key":"dpr","value":"0.8999999761581421","domain":"facebook.com","path":"/","hostOnly":false,"creation":"2022-11-30T22:56:48.751Z","lastAccessed":"2022-11-30T23:00:00.830Z"},{"key":"locale","value":"en_US","domain":"facebook.com","path":"/","hostOnly":false,"creation":"2022-11-30T22:56:48.757Z","lastAccessed":"2022-11-30T23:00:00.830Z"},{"key":"datr","value":"rJmFY8o8CAzOdrR2R3yap1y0","domain":"facebook.com","path":"/","hostOnly":false,"creation":"2022-11-30T22:56:48.761Z","lastAccessed":"2022-11-30T23:00:00.830Z"},{"key":"wd","value":"1517x725","domain":"facebook.com","path":"/","hostOnly":false,"creation":"2022-11-30T22:56:48.763Z","lastAccessed":"2022-11-30T23:00:00.830Z"},{"key":"c_user","value":"100071743848974","domain":"facebook.com","path":"/","hostOnly":false,"creation":"2022-11-30T22:56:48.766Z","lastAccessed":"2022-11-30T23:00:00.830Z"},{"key":"xs","value":"7%3AiBu_j9sVkE-7vw%3A2%3A1669723285%3A-1%3A3222%3A%3AAcWTZN-Ss_FK0iDV560WT0ZnXaA7uPE9lflxZSf9mKk","domain":"facebook.com","path":"/","hostOnly":false,"creation":"2022-11-30T22:56:48.768Z","lastAccessed":"2022-11-30T23:00:00.830Z"},{"key":"fr","value":"0aVrDuAcnqYy2xzaV.AWVUwbvubXH8F773n6mEPgKVozM.Bjh8uY.bq.AAA.0.0.Bjh8uY.AWVRVjCApn0","domain":"facebook.com","path":"/","hostOnly":false,"creation":"2022-11-30T22:56:48.770Z","lastAccessed":"2022-11-30T23:00:00.830Z"},{"key":"m_page_voice","value":"100071743848974","domain":"facebook.com","path":"/","hostOnly":false,"creation":"2022-11-30T22:56:48.772Z","lastAccessed":"2022-11-30T23:00:00.830Z"},{"key":"sb","value":"ivgEYzHzzCO2rmNYNF2gtHb0","domain":"facebook.com","path":"/","hostOnly":false,"creation":"2022-11-30T22:56:48.634Z","lastAccessed":"2022-11-30T23:00:00.830Z"},{"key":"dpr","value":"0.8999999761581421","domain":"facebook.com","path":"/","hostOnly":false,"creation":"2022-11-30T22:56:48.751Z","lastAccessed":"2022-11-30T23:00:00.830Z"},{"key":"locale","value":"en_US","domain":"facebook.com","path":"/","hostOnly":false,"creation":"2022-11-30T22:56:48.757Z","lastAccessed":"2022-11-30T23:00:00.830Z"},{"key":"datr","value":"rJmFY8o8CAzOdrR2R3yap1y0","domain":"facebook.com","path":"/","hostOnly":false,"creation":"2022-11-30T22:56:48.761Z","lastAccessed":"2022-11-30T23:00:00.830Z"},{"key":"wd","value":"1517x725","domain":"facebook.com","path":"/","hostOnly":false,"creation":"2022-11-30T22:56:48.763Z","lastAccessed":"2022-11-30T23:00:00.830Z"},{"key":"c_user","value":"100071743848974","domain":"facebook.com","path":"/","hostOnly":false,"creation":"2022-11-30T22:56:48.766Z","lastAccessed":"2022-11-30T23:00:00.830Z"},{"key":"xs","value":"7%3AiBu_j9sVkE-7vw%3A2%3A1669723285%3A-1%3A3222%3A%3AAcWTZN-Ss_FK0iDV560WT0ZnXaA7uPE9lflxZSf9mKk","domain":"facebook.com","path":"/","hostOnly":false,"creation":"2022-11-30T22:56:48.768Z","lastAccessed":"2022-11-30T23:00:00.830Z"},{"key":"fr","value":"0aVrDuAcnqYy2xzaV.AWVUwbvubXH8F773n6mEPgKVozM.Bjh8uY.bq.AAA.0.0.Bjh8uY.AWVRVjCApn0","domain":"facebook.com","path":"/","hostOnly":false,"creation":"2022-11-30T22:56:48.770Z","lastAccessed":"2022-11-30T23:00:00.830Z"},{"key":"m_page_voice","value":"100071743848974","domain":"facebook.com","path":"/","hostOnly":false,"creation":"2022-11-30T22:56:48.772Z","lastAccessed":"2022-11-30T23:00:00.830Z"},{"key":"m_page_voice","value":"100071743848974","domain":"messenger.com","path":"/","hostOnly":false,"creation":"2022-11-30T22:56:48.863Z","lastAccessed":"2022-11-30T23:00:00.833Z"},{"key":"c_user","value":"100071743848974","domain":"messenger.com","path":"/","hostOnly":false,"creation":"2022-11-30T22:56:48.871Z","lastAccessed":"2022-11-30T23:00:00.833Z"},{"key":"xs","value":"7%3AiBu_j9sVkE-7vw%3A2%3A1669723285%3A-1%3A3222%3A%3AAcWTZN-Ss_FK0iDV560WT0ZnXaA7uPE9lflxZSf9mKk","domain":"messenger.com","path":"/","hostOnly":false,"creation":"2022-11-30T22:56:48.873Z","lastAccessed":"2022-11-30T23:00:00.833Z"},{"key":"fr","value":"0aVrDuAcnqYy2xzaV.AWVUwbvubXH8F773n6mEPgKVozM.Bjh8uY.bq.AAA.0.0.Bjh8uY.AWVRVjCApn0","domain":"messenger.com","path":"/","hostOnly":false,"creation":"2022-11-30T22:56:48.874Z","lastAccessed":"2022-11-30T23:00:00.833Z"}]